ergpy/appkit.py
ergpy/ergo.jar
ergpy/helper_functions.py
ergpy/logs.py
ergpy-0.1.9.1.dist-info/LICENCE.md
ergpy-0.1.9.1.dist-info/METADATA
ergpy-0.1.9.1.dist-info/WHEEL
ergpy-0.1.9.1.dist-info/top_level.txt
ergpy-0.1.9.1.dist-info/RECORD
