Metadata-Version: 2.1
Name: ergpy
Version: 0.1.9.1
Summary: Python-jvm wrapper for interacting with the Ergo Blockchain
Home-page: https://github.com/mgpai22/ergpy
Author: MGpai
License: MIT
Keywords: appkit
License-File: LICENCE.md
Requires-Dist: setuptools (>=40.8.0)
Requires-Dist: JPype1 (>=1.3.0)
Requires-Dist: requests (>=2.27.1)
Requires-Dist: stubgenj (>=0.2.5)
